README.md
setup.py
classes/__init__.py
classes/request_handler.py
classes/router.py
fbgrouting.egg-info/PKG-INFO
fbgrouting.egg-info/SOURCES.txt
fbgrouting.egg-info/dependency_links.txt
fbgrouting.egg-info/top_level.txt