Metadata-Version: 2.1
Name: fbgrouting
Version: 0.1
Summary: fbgrouting - packete de creacion de rutas
Home-page: https://github.com/usuariomen/fbgrouting
Author: Tu Nombre
Author-email: tu.email@example.com
Classifier: Programming Language :: Python :: 3
Classifier: License :: OSI Approved :: MIT License
Classifier: Operating System :: OS Independent
